valdo/VERSION
valdo/__init__.py
valdo/blobs.py
valdo/helper.py
valdo/knn_tools.py
valdo/preprocessing.py
valdo/reindex.py
valdo/scaling.py
valdo/tag.py
valdo/temp.py
valdo/vae_basics.py
valdo/vae_networks.py
valdo/commandline/__init__.py
valdo/commandline/config.py
valdo/commandline/pipeline.py
valdo/commandline/refine.py
rs_valdo-0.0.5.dist-info/METADATA
rs_valdo-0.0.5.dist-info/WHEEL
rs_valdo-0.0.5.dist-info/entry_points.txt
rs_valdo-0.0.5.dist-info/top_level.txt
rs_valdo-0.0.5.dist-info/RECORD
